attrs_to_sql/__init__.py
attrs_to_sql/columns.py
attrs_to_sql/renderer.py
attrs_to_sql/sql_to_attrs.py
attrs_to_sql/table.py
attrs_to_sql/utils.py
attrs_to_sql/templates/attrs.py_
attrs_to_sql/templates/create_table.sql
attrs_to_sql/templates/sqlalchemy_table.py_
attrs_to_sql-0.2.0.dist-info/METADATA
attrs_to_sql-0.2.0.dist-info/RECORD
attrs_to_sql-0.2.0.dist-info/WHEEL
attrs_to_sql-0.2.0.dist-info/top_level.txt
tests/__init__.py
tests/test_table.py
tests/test_utils.py
