Metadata-Version: 2.1
Name: attrs-to-sql
Version: 0.2.0
Summary: Convert attrs class to CREATE TABLE command.
Home-page: https://github.com/potykion/attrs_to_sql
Author: potykion
Author-email: potykion@gmail.com
License: UNKNOWN
Platform: UNKNOWN
Classifier: Programming Language :: Python :: 3
Classifier: License :: OSI Approved :: MIT License
Classifier: Operating System :: OS Independent
Requires-Dist: attrs (>=18.1.0)
Requires-Dist: jinja2 (>=2.10)
